Workbook

Sheet 1_Raw_Data
A1: INPUT DATA — Individual Sales Transactions
A4: Transaction_ID | B4: Date | C4: City | D4: Category | E4: Units | F4: Unit_Price | G4: Sales_Amount | H4: Payment_Mode
A5: TXN001 | B5: 46204 | C5: Mumbai | D5: Electronics | E5: 2 | F5: 2500 | G5: =E5*F5 -> 5000 | H5: UPI
A6: TXN002 | B6: 46204 | C6: Delhi | D6: Clothing | E6: 3 | F6: 1200 | G6: =E6*F6 -> 3600 | H6: Card
A7: TXN003 | B7: 46204 | C7: Mumbai | D7: Grocery | E7: 5 | F7: 300 | G7: =E7*F7 -> 1500 | H7: Cash
A8: TXN004 | B8: 46204 | C8: Bengaluru | D8: Home | E8: 2 | F8: 1800 | G8: =E8*F8 -> 3600 | H8: UPI
A9: TXN005 | B9: 46205 | C9: Delhi | D9: Electronics | E9: 1 | F9: 4000 | G9: =E9*F9 -> 4000 | H9: Card
A10: TXN006 | B10: 46205 | C10: Chennai | D10: Clothing | E10: 4 | F10: 800 | G10: =E10*F10 -> 3200 | H10: UPI
A11: TXN007 | B11: 46205 | C11: Mumbai | D11: Home | E11: 1 | F11: 2200 | G11: =E11*F11 -> 2200 | H11: Wallet
A12: TXN008 | B12: 46205 | C12: Bengaluru | D12: Grocery | E12: 6 | F12: 250 | G12: =E12*F12 -> 1500 | H12: Cash
A13: TXN009 | B13: 46206 | C13: Chennai | D13: Electronics | E13: 2 | F13: 3000 | G13: =E13*F13 -> 6000 | H13: Card
A14: TXN010 | B14: 46206 | C14: Delhi | D14: Grocery | E14: 8 | F14: 200 | G14: =E14*F14 -> 1600 | H14: UPI
A15: TXN011 | B15: 46206 | C15: Mumbai | D15: Clothing | E15: 2 | F15: 1500 | G15: =E15*F15 -> 3000 | H15: Card
A16: TXN012 | B16: 46206 | C16: Bengaluru | D16: Electronics | E16: 1 | F16: 5500 | G16: =E16*F16 -> 5500 | H16: UPI
... A28: TXN024 | B28: 46209 | C28: Bengaluru | D28: Grocery | E28: 9 | F28: 160 | G28: =E28*F28 -> 1440 | H28: Cash

Sheet Output
A1: REDUCE — One Final Business Result per City
A4: City | B4: Total_Sales | C4: Order_Count | D4: Total_Units | E4: Average_Order_Value | F4: Expected_Total | G4: Check
A5: Bengaluru | B5: =SUMIF('1_Raw_Data'!$C$5:$C$28,A5,'1_Raw_Data'!$G$5:$G$28) -> 19740 | C5: =COUNTIF('1_Raw_Data'!$C$5:$C$28,A5) -> 6 | D5: =SUMIF('1_Raw_Data'!$C$5:$C$28,A5,'1_Raw_Data'!$E$5:$E$28) -> 24 | E5: =B5/C5 -> 3290 | F5: 19740 | G5: =IF(B5=F5,"CORRECT","ERROR") -> CORRECT
A6: Chennai | B6: =SUMIF('1_Raw_Data'!$C$5:$C$28,A6,'1_Raw_Data'!$G$5:$G$28) -> 21800 | C6: =COUNTIF('1_Raw_Data'!$C$5:$C$28,A6) -> 5 | D6: =SUMIF('1_Raw_Data'!$C$5:$C$28,A6,'1_Raw_Data'!$E$5:$E$28) -> 20 | E6: =B6/C6 -> 4360 | F6: 21800 | G6: =IF(B6=F6,"CORRECT","ERROR") -> CORRECT
A7: Delhi | B7: =SUMIF('1_Raw_Data'!$C$5:$C$28,A7,'1_Raw_Data'!$G$5:$G$28) -> 22200 | C7: =COUNTIF('1_Raw_Data'!$C$5:$C$28,A7) -> 6 | D7: =SUMIF('1_Raw_Data'!$C$5:$C$28,A7,'1_Raw_Data'!$E$5:$E$28) -> 18 | E7: =B7/C7 -> 3700 | F7: 22200 | G7: =IF(B7=F7,"CORRECT","ERROR") -> CORRECT
A8: Mumbai | B8: =SUMIF('1_Raw_Data'!$C$5:$C$28,A8,'1_Raw_Data'!$G$5:$G$28) -> 23040 | C8: =COUNTIF('1_Raw_Data'!$C$5:$C$28,A8) -> 7 | D8: =SUMIF('1_Raw_Data'!$C$5:$C$28,A8,'1_Raw_Data'!$E$5:$E$28) -> 21 | E8: =B8/C8 -> 3291.4286 | F8: 23040 | G8: =IF(B8=F8,"CORRECT","ERROR") -> CORRECT
A10: Every row should show CORRECT. The Expected_Total column was independently calculated from the raw dataset.
