Workbook

Sheet 1_Raw_Data
A1: INPUT DATA — Individual Sales Transactions
A4: Transaction_ID | B4: Date | C4: City | D4: Category | E4: Units | F4: Unit_Price | G4: Sales_Amount | H4: Payment_Mode
A5: TXN001 | B5: 46204 | C5: Mumbai | D5: Electronics | E5: 2 | F5: 2500 | G5: =E5*F5 -> 5000 | H5: UPI
A6: TXN002 | B6: 46204 | C6: Delhi | D6: Clothing | E6: 3 | F6: 1200 | G6: =E6*F6 -> 3600 | H6: Card
A7: TXN003 | B7: 46204 | C7: Mumbai | D7: Grocery | E7: 5 | F7: 300 | G7: =E7*F7 -> 1500 | H7: Cash
A8: TXN004 | B8: 46204 | C8: Bengaluru | D8: Home | E8: 2 | F8: 1800 | G8: =E8*F8 -> 3600 | H8: UPI
A9: TXN005 | B9: 46205 | C9: Delhi | D9: Electronics | E9: 1 | F9: 4000 | G9: =E9*F9 -> 4000 | H9: Card
A10: TXN006 | B10: 46205 | C10: Chennai | D10: Clothing | E10: 4 | F10: 800 | G10: =E10*F10 -> 3200 | H10: UPI
A11: TXN007 | B11: 46205 | C11: Mumbai | D11: Home | E11: 1 | F11: 2200 | G11: =E11*F11 -> 2200 | H11: Wallet
A12: TXN008 | B12: 46205 | C12: Bengaluru | D12: Grocery | E12: 6 | F12: 250 | G12: =E12*F12 -> 1500 | H12: Cash
A13: TXN009 | B13: 46206 | C13: Chennai | D13: Electronics | E13: 2 | F13: 3000 | G13: =E13*F13 -> 6000 | H13: Card
A14: TXN010 | B14: 46206 | C14: Delhi | D14: Grocery | E14: 8 | F14: 200 | G14: =E14*F14 -> 1600 | H14: UPI
A15: TXN011 | B15: 46206 | C15: Mumbai | D15: Clothing | E15: 2 | F15: 1500 | G15: =E15*F15 -> 3000 | H15: Card
A16: TXN012 | B16: 46206 | C16: Bengaluru | D16: Electronics | E16: 1 | F16: 5500 | G16: =E16*F16 -> 5500 | H16: UPI
... A28: TXN024 | B28: 46209 | C28: Bengaluru | D28: Grocery | E28: 9 | F28: 160 | G28: =E28*F28 -> 1440 | H28: Cash

Sheet 2_Map
A1: MAP — Turn Each Transaction into City → Sales Amount
A4: Transaction_ID | B4: Original_City | C4: Original_Sales | D4: Map_Key | E4: Map_Value | F4: Map_Output
A5: ='1_Raw_Data'!A5 -> TXN001 | B5: ='1_Raw_Data'!C5 -> Mumbai | C5: ='1_Raw_Data'!G5 -> 5000 | D5: =B5 -> Mumbai | E5: =C5 -> 5000 | F5: =D5&" → ₹"&TEXT(E5,"#,##0") -> Mumbai → ₹5,000
A6: ='1_Raw_Data'!A6 -> TXN002 | B6: ='1_Raw_Data'!C6 -> Delhi | C6: ='1_Raw_Data'!G6 -> 3600 | D6: =B6 -> Delhi | E6: =C6 -> 3600 | F6: =D6&" → ₹"&TEXT(E6,"#,##0") -> Delhi → ₹3,600
A7: ='1_Raw_Data'!A7 -> TXN003 | B7: ='1_Raw_Data'!C7 -> Mumbai | C7: ='1_Raw_Data'!G7 -> 1500 | D7: =B7 -> Mumbai | E7: =C7 -> 1500 | F7: =D7&" → ₹"&TEXT(E7,"#,##0") -> Mumbai → ₹1,500
A8: ='1_Raw_Data'!A8 -> TXN004 | B8: ='1_Raw_Data'!C8 -> Bengaluru | C8: ='1_Raw_Data'!G8 -> 3600 | D8: =B8 -> Bengaluru | E8: =C8 -> 3600 | F8: =D8&" → ₹"&TEXT(E8,"#,##0") -> Bengaluru → ₹3,600
A9: ='1_Raw_Data'!A9 -> TXN005 | B9: ='1_Raw_Data'!C9 -> Delhi | C9: ='1_Raw_Data'!G9 -> 4000 | D9: =B9 -> Delhi | E9: =C9 -> 4000 | F9: =D9&" → ₹"&TEXT(E9,"#,##0") -> Delhi → ₹4,000
A10: ='1_Raw_Data'!A10 -> TXN006 | B10: ='1_Raw_Data'!C10 -> Chennai | C10: ='1_Raw_Data'!G10 -> 3200 | D10: =B10 -> Chennai | E10: =C10 -> 3200 | F10: =D10&" → ₹"&TEXT(E10,"#,##0") -> Chennai → ₹3,200
A11: ='1_Raw_Data'!A11 -> TXN007 | B11: ='1_Raw_Data'!C11 -> Mumbai | C11: ='1_Raw_Data'!G11 -> 2200 | D11: =B11 -> Mumbai | E11: =C11 -> 2200 | F11: =D11&" → ₹"&TEXT(E11,"#,##0") -> Mumbai → ₹2,200
A12: ='1_Raw_Data'!A12 -> TXN008 | B12: ='1_Raw_Data'!C12 -> Bengaluru | C12: ='1_Raw_Data'!G12 -> 1500 | D12: =B12 -> Bengaluru | E12: =C12 -> 1500 | F12: =D12&" → ₹"&TEXT(E12,"#,##0") -> Bengaluru → ₹1,500
A13: ='1_Raw_Data'!A13 -> TXN009 | B13: ='1_Raw_Data'!C13 -> Chennai | C13: ='1_Raw_Data'!G13 -> 6000 | D13: =B13 -> Chennai | E13: =C13 -> 6000 | F13: =D13&" → ₹"&TEXT(E13,"#,##0") -> Chennai → ₹6,000
A14: ='1_Raw_Data'!A14 -> TXN010 | B14: ='1_Raw_Data'!C14 -> Delhi | C14: ='1_Raw_Data'!G14 -> 1600 | D14: =B14 -> Delhi | E14: =C14 -> 1600 | F14: =D14&" → ₹"&TEXT(E14,"#,##0") -> Delhi → ₹1,600
A15: ='1_Raw_Data'!A15 -> TXN011 | B15: ='1_Raw_Data'!C15 -> Mumbai | C15: ='1_Raw_Data'!G15 -> 3000 | D15: =B15 -> Mumbai | E15: =C15 -> 3000 | F15: =D15&" → ₹"&TEXT(E15,"#,##0") -> Mumbai → ₹3,000
A16: ='1_Raw_Data'!A16 -> TXN012 | B16: ='1_Raw_Data'!C16 -> Bengaluru | C16: ='1_Raw_Data'!G16 -> 5500 | D16: =B16 -> Bengaluru | E16: =C16 -> 5500 | F16: =D16&" → ₹"&TEXT(E16,"#,##0") -> Bengaluru → ₹5,500
... A28: ='1_Raw_Data'!A28 -> TXN024 | B28: ='1_Raw_Data'!C28 -> Bengaluru | C28: ='1_Raw_Data'!G28 -> 1440 | D28: =B28 -> Bengaluru | E28: =C28 -> 1440 | F28: =D28&" → ₹"&TEXT(E28,"#,##0") -> Bengaluru → ₹1,440

Sheet 3_Shuffle
A1: SHUFFLE — Same City Keys Grouped Together
A4: City_Key | B4: Sales_Value | C4: Source_Transaction | D4: What Happened
A5: Bengaluru | B5: 3600 | C5: TXN004 | D5: Grouped under Bengaluru
A6: Bengaluru | B6: 1500 | C6: TXN008 | D6: Grouped under Bengaluru
A7: Bengaluru | B7: 5500 | C7: TXN012 | D7: Grouped under Bengaluru
A8: Bengaluru | B8: 4500 | C8: TXN016 | D8: Grouped under Bengaluru
A9: Bengaluru | B9: 3200 | C9: TXN020 | D9: Grouped under Bengaluru
A10: Bengaluru | B10: 1440 | C10: TXN024 | D10: Grouped under Bengaluru
A11: Chennai | B11: 3200 | C11: TXN006 | D11: Grouped under Chennai
A12: Chennai | B12: 6000 | C12: TXN009 | D12: Grouped under Chennai
A13: Chennai | B13: 3600 | C13: TXN013 | D13: Grouped under Chennai
A14: Chennai | B14: 1800 | C14: TXN017 | D14: Grouped under Chennai
A15: Chennai | B15: 7200 | C15: TXN021 | D15: Grouped under Chennai
A16: Delhi | B16: 3600 | C16: TXN002 | D16: Grouped under Delhi
... A28: Mumbai | B28: 3300 | C28: TXN023 | D28: Grouped under Mumbai

Sheet 4_Reduce
A1: REDUCE — One Final Business Result per City
A4: City | B4: Total_Sales | C4: Order_Count | D4: Total_Units | E4: Average_Order_Value | F4: Expected_Total | G4: Check
A5: Bengaluru | B5: =SUMIF('1_Raw_Data'!$C$5:$C$28,A5,'1_Raw_Data'!$G$5:$G$28) -> 19740 | C5: =COUNTIF('1_Raw_Data'!$C$5:$C$28,A5) -> 6 | D5: =SUMIF('1_Raw_Data'!$C$5:$C$28,A5,'1_Raw_Data'!$E$5:$E$28) -> 24 | E5: =B5/C5 -> 3290 | F5: 19740 | G5: =IF(B5=F5,"CORRECT","ERROR") -> CORRECT
A6: Chennai | B6: =SUMIF('1_Raw_Data'!$C$5:$C$28,A6,'1_Raw_Data'!$G$5:$G$28) -> 21800 | C6: =COUNTIF('1_Raw_Data'!$C$5:$C$28,A6) -> 5 | D6: =SUMIF('1_Raw_Data'!$C$5:$C$28,A6,'1_Raw_Data'!$E$5:$E$28) -> 20 | E6: =B6/C6 -> 4360 | F6: 21800 | G6: =IF(B6=F6,"CORRECT","ERROR") -> CORRECT
A7: Delhi | B7: =SUMIF('1_Raw_Data'!$C$5:$C$28,A7,'1_Raw_Data'!$G$5:$G$28) -> 22200 | C7: =COUNTIF('1_Raw_Data'!$C$5:$C$28,A7) -> 6 | D7: =SUMIF('1_Raw_Data'!$C$5:$C$28,A7,'1_Raw_Data'!$E$5:$E$28) -> 18 | E7: =B7/C7 -> 3700 | F7: 22200 | G7: =IF(B7=F7,"CORRECT","ERROR") -> CORRECT
A8: Mumbai | B8: =SUMIF('1_Raw_Data'!$C$5:$C$28,A8,'1_Raw_Data'!$G$5:$G$28) -> 23040 | C8: =COUNTIF('1_Raw_Data'!$C$5:$C$28,A8) -> 7 | D8: =SUMIF('1_Raw_Data'!$C$5:$C$28,A8,'1_Raw_Data'!$E$5:$E$28) -> 21 | E8: =B8/C8 -> 3291.4286 | F8: 23040 | G8: =IF(B8=F8,"CORRECT","ERROR") -> CORRECT
A10: Every row should show CORRECT. The Expected_Total column was independently calculated from the raw dataset.

Sheet 5_Explanation
A1: How to Read This Workbook
A4: Stage | B4: Business Meaning | C4: Example | D4: Where to See It
A5: Input | B5: Individual sales bills | C5: Mumbai sale of ₹5,000 | D5: 1_Raw_Data
A6: Map | B6: Label each bill by city | C6: Mumbai → ₹5,000 | D6: 2_Map
A7: Shuffle | B7: Put all Mumbai bills together | C7: Mumbai values appear together | D7: 3_Shuffle
A8: Reduce | B8: Add all Mumbai bills | C8: Mumbai total sales | D8: 4_Reduce
